smartscope/__init__.py
smartscope/bibtex.py
smartscope/constants.py
smartscope/icon.png
smartscope/protocols.conf
smartscope/objects/__init__.py
smartscope/objects/data.py
smartscope/objects/dataCollection.py
smartscope/objects/data_deprecated.py
smartscope/protocols/__init__.py
smartscope/protocols/protocol_feedback.py
smartscope/protocols/protocol_importAtlas.py
smartscope/protocols/protocol_provide_calculations.py
smartscope/protocols/protocol_smartscope.py
smartscope/viewers/__init__.py
smartscope/viewers/viewer_data.py
smartscope/wizards/__init__.py
smartscope/wizards/wizard_list_sessions.py
scipion_em_smartscope-3.0.1.dist-info/LICENSE
scipion_em_smartscope-3.0.1.dist-info/METADATA
scipion_em_smartscope-3.0.1.dist-info/WHEEL
scipion_em_smartscope-3.0.1.dist-info/entry_points.txt
scipion_em_smartscope-3.0.1.dist-info/top_level.txt
scipion_em_smartscope-3.0.1.dist-info/RECORD
