Metadata-Version: 2.1
Name: scipion-em-smartscope
Version: 3.0.1
Summary: Plugin to manage Smartscope from Scipion
Home-page: https://github.com/scipion-em/scipion-em-smartscope
Author: Daniel Marchan and Alberto Garcia Mena
Author-email: da.marchan@cnb.csic.es, alberto.garcia@cnb.csic.es
License: UNKNOWN
Keywords: scipion cryoem imageprocessing scipion-3.0 screening smartscope
Platform: UNKNOWN
Requires-Dist: scipion-pyworkflow
Requires-Dist: scipion-em
Requires-Dist: requests
Requires-Dist: scipion-em-xmipp
Requires-Dist: Pathlib
